python_tado_async/__init__.py
python_tado_async/const.py
python_tado_async/exceptions.py
python_tado_async/models.py
python_tado_async/py.typed
python_tado_async/python_tado_async.py
python_tado_async-0.1.5.dist-info/LICENSE.md
python_tado_async-0.1.5.dist-info/METADATA
python_tado_async-0.1.5.dist-info/WHEEL
python_tado_async-0.1.5.dist-info/RECORD
